LICENSE
MANIFEST.in
README.md
setup.cfg
setup.py
automl/__init__.py
automl/automl_restful.py
automl/classifier_algorithms.py
automl/default_algorithms.yml
automl/default_processor.yml
automl/estimator.py
automl/hyper_config.py
automl/model_ensemble.py
automl/model_selection.py
automl/neural_network_search.py
automl/pipeline_training.py
automl/preprocessing.py
automl/regressor_algorithms.py
automl/scorer.py
automl/search_hypers.yml
automl/pro_test/__init__.py
automl/pro_test/get_test_data.py
automl/pro_test/test_auto_ml.py
automl/utils/CONSTANT.py
automl/utils/__init__.py
automl/utils/backend_obj.py
automl/utils/data_rela.py
automl/utils/func_utils.py
automl/utils/logger.py
automl/utils/paths.py
automl_engine.egg-info/PKG-INFO
automl_engine.egg-info/SOURCES.txt
automl_engine.egg-info/dependency_links.txt
automl_engine.egg-info/requires.txt
automl_engine.egg-info/top_level.txt