Metadata-Version: 2.1
Name: automl-engine
Version: 0.0.6
Summary: 3 lines of code for automate machine learning for classification and regression.
Home-page: https://github.com/lugq1990/automl-engine
Author: guangqiang.lu
Author-email: gqianglu@outlook.com
License: MIT License
Platform: any
Classifier: Development Status :: 3 - Alpha
Classifier: Programming Language :: Python
Classifier: Programming Language :: Python :: 3
Classifier: Programming Language :: Python :: 3.5
Classifier: Programming Language :: Python :: 3.6
Classifier: Intended Audience :: Developers
Classifier: Operating System :: OS Independent
License-File: LICENSE
